{
  "id": 67, 
  "title": "Self-signed TLS/SSL certificate", 
  "severity": "medium", 
  "description": {
    "$ref": "#/files/description/67"
  }, 
  "fix": {
    "effort": 60, 
    "guidance": {
      "$ref": "#/files/fix/12"
    }
  }, 
  "cwe": [
    "296"
  ], 
  "tags": [
    "web", 
    "unencrypted", 
    "tls", 
    "ssl"
  ], 
  "references": [
    {
      "url": "https://en.wikipedia.org/wiki/Self-signed_certificate", 
      "title": "Wikipedia article on self-signed certificates"
    }
  ]
}